php_framework_detector/__init__.py
php_framework_detector/__main__.py
php_framework_detector/cli.py
php_framework_detector/core/__init__.py
php_framework_detector/core/__init__.pyi
php_framework_detector/core/detector.py
php_framework_detector/core/exceptions.py
php_framework_detector/core/factory.py
php_framework_detector/core/models.py
php_framework_detector/examples/enum_usage_example.py
php_framework_detector/frameworks/__init__.py
php_framework_detector/frameworks/cakephp.py
php_framework_detector/frameworks/codeigniter.py
php_framework_detector/frameworks/drupal.py
php_framework_detector/frameworks/drush.py
php_framework_detector/frameworks/fastroute.py
php_framework_detector/frameworks/fatfree.py
php_framework_detector/frameworks/fuel.py
php_framework_detector/frameworks/laminas.py
php_framework_detector/frameworks/laravel.py
php_framework_detector/frameworks/phalcon.py
php_framework_detector/frameworks/phpixie.py
php_framework_detector/frameworks/popphp.py
php_framework_detector/frameworks/slim.py
php_framework_detector/frameworks/symfony.py
php_framework_detector/frameworks/thinkphp.py
php_framework_detector/frameworks/yii.py
php_framework_detector/frameworks/zendframework.py
php_framework_detector-0.2.16.dist-info/METADATA
php_framework_detector-0.2.16.dist-info/WHEEL
php_framework_detector-0.2.16.dist-info/entry_points.txt
php_framework_detector-0.2.16.dist-info/RECORD
